odoo/addons/multi_pms_properties/README.rst
odoo/addons/multi_pms_properties/__init__.py
odoo/addons/multi_pms_properties/__manifest__.py
odoo/addons/multi_pms_properties/models.py
odoo/addons/multi_pms_properties/i18n/de.po
odoo/addons/multi_pms_properties/i18n/it.po
odoo/addons/multi_pms_properties/i18n/multi_pms_properties.pot
odoo/addons/multi_pms_properties/readme/CONTRIBUTORS.md
odoo/addons/multi_pms_properties/readme/DESCRIPTION.md
odoo/addons/multi_pms_properties/readme/INSTALL.md
odoo/addons/multi_pms_properties/readme/USAGE.md
odoo/addons/multi_pms_properties/static/description/icon.png
odoo/addons/multi_pms_properties/static/description/index.html
odoo/addons/multi_pms_properties/tests/__init__.py
odoo/addons/multi_pms_properties/tests/common.py
odoo/addons/multi_pms_properties/tests/multi_pms_properties_tester.py
odoo/addons/multi_pms_properties/tests/test_multi_pms_properties.py
odoo_addon_multi_pms_properties-18.0.1.0.0.2.dist-info/METADATA
odoo_addon_multi_pms_properties-18.0.1.0.0.2.dist-info/WHEEL
odoo_addon_multi_pms_properties-18.0.1.0.0.2.dist-info/top_level.txt
odoo_addon_multi_pms_properties-18.0.1.0.0.2.dist-info/RECORD
