Metadata-Version: 2.1
Name: odoo-addon-multi_pms_properties
Version: 18.0.1.0.0.2
Requires-Python: >=3.10
Requires-Dist: odoo==18.0.*
Summary: Multi Properties Manager
Home-page: https://github.com/OCA/pms
License: AGPL-3
Author: Commit [Sun], Odoo Community Association (OCA)
Author-email: support@odoo-community.org
Classifier: Programming Language :: Python
Classifier: Framework :: Odoo
Classifier: Framework :: Odoo :: 18.0
Classifier: License :: OSI Approved :: GNU Affero General Public License v3
